manager_api/__init__.py
manager_api/enums.py
manager_api/model.py
manager_api/object.py
manager_api-0.1.5.dist-info/LICENSE
manager_api-0.1.5.dist-info/METADATA
manager_api-0.1.5.dist-info/WHEEL
manager_api-0.1.5.dist-info/top_level.txt
manager_api-0.1.5.dist-info/RECORD
