Metadata-Version: 2.1
Name: manager-api
Version: 0.1.5
Summary: Python module to access the API provided by Manager accounting software 
Home-page: https://github.com/isotherm/python-manager-api/
Author: Kirk Meyer
Author-email: kirk.meyer@alpaxo.com
License: MIT
Platform: any
Classifier: Development Status :: 3 - Alpha
Classifier: Environment :: Web Environment
Classifier: Intended Audience :: Developers
Classifier: License :: OSI Approved :: MIT License
Classifier: Operating System :: OS Independent
Classifier: Programming Language :: Python :: 3.9
Classifier: Topic :: Office/Business :: Financial :: Accounting
Classifier: Topic :: Software Development :: Libraries :: Python Modules
License-File: LICENSE
Requires-Dist: pydantic (==1.10.20)
